[
    {
        "objectID": "10154",
        "colorValue": [
            75,
            68,
            42
        ],
        "objectImage": "https://images.metmuseum.org/CRDImages/ad/original/DT82.jpg",
        "artistName": "Albert Bierstadt",
        "department": "The American Wing",
        "culture": "American",
        "title": "The Rocky Mountains, Lander's Peak",
        "date": 1863,
        "url": "https://www.metmuseum.org/art/collection/search/10154",
        "season": "Summer"
    },
    {
        "objectID": "11317",
        "colorValue": [
            179,
            171,
            144
        ],
        "objectImage": "https://images.metmuseum.org/CRDImages/ad/original/ap74.25.jpg",
        "artistName": "John Frederick Kensett",
        "department": "The American Wing",
        "culture": "American",
        "title": "October in the Marshes",
        "date": 1872,
        "url": "https://www.metmuseum.org/art/collection/search/11317",
        "season": "Summer"
    },
    {
        "objectID": "10207",
        "colorValue": [
            162,
            133,
            107
        ],
        "objectImage": "https://images.metmuseum.org/CRDImages/ad/original/DT2101.jpg",
        "artistName": "William Bradford",
        "department": "The American Wing",
        "culture": "American",
        "title": "An Arctic Summer: Boring Through the Pack in Melville Bay",
        "date": 1871,
        "url": "https://www.metmuseum.org/art/collection/search/10207",
        "season": "Summer"
    },
    {
        "objectID": "12802",
        "colorValue": [
            67,
            55,
            41
        ],
        "objectImage": "https://images.metmuseum.org/CRDImages/ad/original/ap1984.252.1.jpg",
        "artistName": "Jerome B. Thompson",
        "department": "The American Wing",
        "culture": "American",
        "title": "Summer Flowers",
        "date": 1859,
        "url": "https://www.metmuseum.org/art/collection/search/12802",
        "season": "Summer"
    },
    {
        "objectID": "10788",
        "colorValue": [
            176,
            184,
            175
        ],
        "objectImage": "https://images.metmuseum.org/CRDImages/ad/original/ap77.3.1.jpg",
        "artistName": "Asher Brown Durand",
        "department": "The American Wing",
        "culture": "American",
        "title": "High Point: Shandaken Mountains",
        "date": 1853,
        "url": "https://www.metmuseum.org/art/collection/search/10788",
        "season": "Summer"
    },
    {
        "objectID": "36049",
        "colorValue": [
            141,
            114,
            81
        ],
        "objectImage": "https://images.metmuseum.org/CRDImages/as/original/DP201351_CRD.jpg",
        "artistName": "Unidentified Artist",
        "department": "Asian Art",
        "culture": "China",
        "title": "Streams and Mountains Without End",
        "date": 1600,
        "url": "https://www.metmuseum.org/art/collection/search/36049",
        "season": "Summer"
    },
    {
        "objectID": "11318",
        "colorValue": [
            189,
            183,
            165
        ],
        "objectImage": "https://images.metmuseum.org/CRDImages/ad/original/ap74.38.jpg",
        "artistName": "John Frederick Kensett",
        "department": "The American Wing",
        "culture": "American",
        "title": "The Old Pine, Darien, Connecticut",
        "date": 1872,
        "url": "https://www.metmuseum.org/art/collection/search/11318",
        "season": "Summer"
    },
    {
        "objectID": "36131",
        "colorValue": [
            194,
            172,
            147
        ],
        "objectImage": "https://images.metmuseum.org/CRDImages/as/original/1981_4_1a.jpg",
        "artistName": "Gong Xian",
        "department": "Asian Art",
        "culture": "China",
        "title": "Landscapes with Poems",
        "date": 1688,
        "url": "https://www.metmuseum.org/art/collection/search/36131",
        "season": "Summer"
    },
    {
        "objectID": "10946",
        "colorValue": [
            216,
            191,
            149
        ],
        "objectImage": "https://images.metmuseum.org/CRDImages/ad/original/DT81.jpg",
        "artistName": "Sanford Robinson Gifford",
        "department": "The American Wing",
        "culture": "American",
        "title": "A Gorge in the Mountains (Kauterskill Clove)",
        "date": 1862,
        "url": "https://www.metmuseum.org/art/collection/search/10946",
        "season": "Summer"
    },
    {
        "objectID": "36027",
        "colorValue": [
            140,
            135,
            130
        ],
        "objectImage": "https://images.metmuseum.org/CRDImages/as/original/13_220_123_O1_sf.jpg",
        "artistName": "Zhang Geng",
        "department": "Asian Art",
        "culture": "China",
        "title": "Landscape After Wang Meng",
        "date": 1759,
        "url": "https://www.metmuseum.org/art/collection/search/36027",
        "season": "Summer"
    },
    {
        "objectID": "36436",
        "colorValue": [
            210,
            200,
            185
        ],
        "objectImage": "https://images.metmuseum.org/CRDImages/as/original/DP162771.jpg",
        "artistName": "Zhang Feng",
        "department": "Asian Art",
        "culture": "China",
        "title": "Landscapes",
        "date": 1644,
        "url": "https://www.metmuseum.org/art/collection/search/36436",
        "season": "Summer"
    },
    {
        "objectID": "39915",
        "colorValue": [
            104,
            90,
            69
        ],
        "objectImage": "https://images.metmuseum.org/CRDImages/as/original/DP226465.jpg",
        "artistName": "Qu Ding",
        "department": "Asian Art",
        "culture": "China",
        "title": "Summer Mountains",
        "date": 1040,
        "url": "https://www.metmuseum.org/art/collection/search/39915",
        "season": "Summer"
    },
    {
        "objectID": "36135",
        "colorValue": [
            203,
            193,
            188
        ],
        "objectImage": "https://images.metmuseum.org/CRDImages/as/original/DT9400.jpg",
        "artistName": "Wen Jia",
        "department": "Asian Art",
        "culture": "China",
        "title": "Landscape Dedicated to Xiang Yuanbian",
        "date": 1578,
        "url": "https://www.metmuseum.org/art/collection/search/36135",
        "season": "Summer"
    },
    {
        "objectID": "39959",
        "colorValue": [
            112,
            85,
            57
        ],
        "objectImage": "https://images.metmuseum.org/CRDImages/as/original/DP165265_CRD.jpg",
        "artistName": "Yang Bangji",
        "department": "Asian Art",
        "culture": "China",
        "title": "A Diplomatic Mission to the Jin",
        "date": 1156,
        "url": "https://www.metmuseum.org/art/collection/search/39959",
        "season": "Summer"
    },
    {
        "objectID": "40002",
        "colorValue": [
            78,
            64,
            48
        ],
        "objectImage": "https://images.metmuseum.org/CRDImages/as/original/DP165244.jpg",
        "artistName": "Unidentified Artist",
        "department": "Asian Art",
        "culture": "China",
        "title": "Landscape in the style of Fan Kuan",
        "date": 1100,
        "url": "https://www.metmuseum.org/art/collection/search/40002",
        "season": "Summer"
    },
    {
        "objectID": "40007",
        "colorValue": [
            154,
            133,
            116
        ],
        "objectImage": "https://images.metmuseum.org/CRDImages/as/original/DP212993_4_CRD.jpg",
        "artistName": "Mi Youren",
        "department": "Asian Art",
        "culture": "China",
        "title": "Cloudy Mountains",
        "date": 1127,
        "url": "https://www.metmuseum.org/art/collection/search/40007",
        "season": "Summer"
    },
    {
        "objectID": "40062",
        "colorValue": [
            237,
            228,
            208
        ],
        "objectImage": "https://images.metmuseum.org/CRDImages/as/original/DP154096.jpg",
        "artistName": "Yan Ciyu",
        "department": "Asian Art",
        "culture": "China",
        "title": "Hermitage by a Pine-covered Bluff",
        "date": 1164,
        "url": "https://www.metmuseum.org/art/collection/search/40062",
        "season": "Summer"
    },
    {
        "objectID": "42347",
        "colorValue": [
            158,
            134,
            101
        ],
        "objectImage": "https://images.metmuseum.org/CRDImages/as/original/DT8176.jpg",
        "artistName": "",
        "department": "Asian Art",
        "culture": "Japan",
        "title": "Eight Views of the Xiao and Xiang Rivers",
        "date": 1500,
        "url": "https://www.metmuseum.org/art/collection/search/42347",
        "season": "Summer"
    },
    {
        "objectID": "41479",
        "colorValue": [
            171,
            157,
            141
        ],
        "objectImage": "https://images.metmuseum.org/CRDImages/as/original/DP216493_94.jpg",
        "artistName": "Dong Qichang",
        "department": "Asian Art",
        "culture": "China",
        "title": "Invitation to Reclusion at Jingxi",
        "date": 1611,
        "url": "https://www.metmuseum.org/art/collection/search/41479",
        "season": "Summer"
    },
    {
        "objectID": "42493",
        "colorValue": [
            158,
            134,
            101
        ],
        "objectImage": "https://images.metmuseum.org/CRDImages/as/original/DT8176.jpg",
        "artistName": "",
        "department": "Asian Art",
        "culture": "Japan",
        "title": "Eight Views of the Xiao and Xiang Rivers",
        "date": 1500,
        "url": "https://www.metmuseum.org/art/collection/search/42493",
        "season": "Summer"
    },
    {
        "objectID": "435655",
        "colorValue": [
            64,
            43,
            22
        ],
        "objectImage": "https://images.metmuseum.org/CRDImages/ep/original/DP143195.jpg",
        "artistName": "Nicolaes Berchem",
        "department": "European Paintings",
        "culture": "",
        "title": "Rest",
        "date": 1644,
        "url": "https://www.metmuseum.org/art/collection/search/435655",
        "season": "Summer"
    },
    {
        "objectID": "435707",
        "colorValue": [
            179,
            176,
            166
        ],
        "objectImage": "https://images.metmuseum.org/CRDImages/ep/original/DP164827.jpg",
        "artistName": "Richard Parkes Bonington",
        "department": "European Paintings",
        "culture": "",
        "title": "Roadside Halt",
        "date": 1826,
        "url": "https://www.metmuseum.org/art/collection/search/435707",
        "season": "Summer"
    },
    {
        "objectID": "435684",
        "colorValue": [
            67,
            67,
            67
        ],
        "objectImage": "https://images.metmuseum.org/CRDImages/ep/original/ep26.100.bw.R.jpg",
        "artistName": "Arnold Böcklin",
        "department": "European Paintings",
        "culture": "",
        "title": "Roman Landscape",
        "date": 1850,
        "url": "https://www.metmuseum.org/art/collection/search/435684",
        "season": "Summer"
    },
    {
        "objectID": "435809",
        "colorValue": [
            152,
            116,
            69
        ],
        "objectImage": "https://images.metmuseum.org/CRDImages/ep/original/DP119115.jpg",
        "artistName": "Pieter Bruegel the Elder",
        "department": "European Paintings",
        "culture": "",
        "title": "The Harvesters",
        "date": 1565,
        "url": "https://www.metmuseum.org/art/collection/search/435809",
        "season": "Summer"
    },
    {
        "objectID": "435879",
        "colorValue": [
            80,
            100,
            95
        ],
        "objectImage": "https://images.metmuseum.org/CRDImages/ep/original/DT1492.jpg",
        "artistName": "Paul Cézanne",
        "department": "European Paintings",
        "culture": "",
        "title": "The Pool at Jas de Bouffan",
        "date": 1885,
        "url": "https://www.metmuseum.org/art/collection/search/435879",
        "season": "Summer"
    },
    {
        "objectID": "436060",
        "colorValue": [
            51,
            35,
            20
        ],
        "objectImage": "https://images.metmuseum.org/CRDImages/ep/original/DP143164.jpg",
        "artistName": "Abraham van Cuylenborch",
        "department": "European Paintings",
        "culture": "",
        "title": "Bacchus and Nymphs in a Landscape",
        "date": 1640,
        "url": "https://www.metmuseum.org/art/collection/search/436060",
        "season": "Summer"
    },
    {
        "objectID": "435923",
        "colorValue": [
            61,
            58,
            44
        ],
        "objectImage": "https://images.metmuseum.org/CRDImages/ep/original/DP164805.jpg",
        "artistName": "John Constable",
        "department": "European Paintings",
        "culture": "",
        "title": "Stoke-by-Nayland",
        "date": 1805,
        "url": "https://www.metmuseum.org/art/collection/search/435923",
        "season": "Summer"
    },
    {
        "objectID": "436083",
        "colorValue": [
            233,
            221,
            201
        ],
        "objectImage": "https://images.metmuseum.org/CRDImages/ep/original/EP1038.jpg",
        "artistName": "Charles-François Daubigny",
        "department": "European Paintings",
        "culture": "",
        "title": "A River Landscape with Storks",
        "date": 1864,
        "url": "https://www.metmuseum.org/art/collection/search/436083",
        "season": "Summer"
    },
    {
        "objectID": "436241",
        "colorValue": [
            211,
            197,
            157
        ],
        "objectImage": "https://images.metmuseum.org/CRDImages/ep/original/DP232030.jpg",
        "artistName": "Jules Dupré",
        "department": "European Paintings",
        "culture": "",
        "title": "Cows Crossing a Ford",
        "date": 1836,
        "url": "https://www.metmuseum.org/art/collection/search/436241",
        "season": "Summer"
    },
    {
        "objectID": "436441",
        "colorValue": [
            61,
            50,
            33
        ],
        "objectImage": "https://images.metmuseum.org/CRDImages/ep/original/DP123922.jpg",
        "artistName": "Thomas Gainsborough",
        "department": "European Paintings",
        "culture": "",
        "title": "Wooded Upland Landscape",
        "date": 1783,
        "url": "https://www.metmuseum.org/art/collection/search/436441",
        "season": "Summer"
    },
    {
        "objectID": "436455",
        "colorValue": [
            54,
            37,
            27
        ],
        "objectImage": "https://images.metmuseum.org/CRDImages/ep/original/DT2138.jpg",
        "artistName": "Théodore Gericault",
        "department": "European Paintings",
        "culture": "",
        "title": "Evening: Landscape with an Aqueduct",
        "date": 1818,
        "url": "https://www.metmuseum.org/art/collection/search/436455",
        "season": "Summer"
    },
    {
        "objectID": "436558",
        "colorValue": [
            123,
            119,
            102
        ],
        "objectImage": "https://images.metmuseum.org/CRDImages/ep/original/DP146495.jpg",
        "artistName": "Jan van Goyen",
        "department": "European Paintings",
        "culture": "",
        "title": "View of Haarlem and the Haarlemmer Meer",
        "date": 1646,
        "url": "https://www.metmuseum.org/art/collection/search/436558",
        "season": "Summer"
    },
    {
        "objectID": "436952",
        "colorValue": [
            58,
            74,
            63
        ],
        "objectImage": "https://images.metmuseum.org/CRDImages/ep/original/DT1931.jpg",
        "artistName": "Edouard Manet",
        "department": "European Paintings",
        "culture": "",
        "title": "The Funeral",
        "date": 1867,
        "url": "https://www.metmuseum.org/art/collection/search/436952",
        "season": "Summer"
    },
    {
        "objectID": "437191",
        "colorValue": [
            54,
            47,
            32
        ],
        "objectImage": "https://images.metmuseum.org/CRDImages/ep/original/DP146446.jpg",
        "artistName": "Aert van der Neer",
        "department": "European Paintings",
        "culture": "",
        "title": "Landscape at Sunset",
        "date": 1650,
        "url": "https://www.metmuseum.org/art/collection/search/437191",
        "season": "Summer"
    },
    {
        "objectID": "437102",
        "colorValue": [
            135,
            138,
            121
        ],
        "objectImage": "https://images.metmuseum.org/CRDImages/ep/original/DP146459.jpg",
        "artistName": "Pieter de Molijn",
        "department": "European Paintings",
        "culture": "",
        "title": "Landscape with a Cottage",
        "date": 1629,
        "url": "https://www.metmuseum.org/art/collection/search/437102",
        "season": "Summer"
    },
    {
        "objectID": "437323",
        "colorValue": [
            141,
            148,
            139
        ],
        "objectImage": "https://images.metmuseum.org/CRDImages/ep/original/DP145952.jpg",
        "artistName": "Frans Post",
        "department": "European Paintings",
        "culture": "",
        "title": "A Brazilian Landscape",
        "date": 1650,
        "url": "https://www.metmuseum.org/art/collection/search/437323",
        "season": "Summer"
    },
    {
        "objectID": "437316",
        "colorValue": [
            67,
            67,
            44
        ],
        "objectImage": "https://images.metmuseum.org/CRDImages/ep/original/DT1043.jpg",
        "artistName": "Camille Pissarro",
        "department": "European Paintings",
        "culture": "",
        "title": "Côte des Grouettes, near Pontoise",
        "date": 1878,
        "url": "https://www.metmuseum.org/art/collection/search/437316",
        "season": "Summer"
    },
    {
        "objectID": "437516",
        "colorValue": [
            36,
            29,
            18
        ],
        "objectImage": "https://images.metmuseum.org/CRDImages/ep/original/ep3.28.R.jpg",
        "artistName": "Théodore Rousseau",
        "department": "European Paintings",
        "culture": "",
        "title": "An Old Chapel in a Valley",
        "date": 1832,
        "url": "https://www.metmuseum.org/art/collection/search/437516",
        "season": "Summer"
    },
    {
        "objectID": "437547",
        "colorValue": [
            118,
            119,
            99
        ],
        "objectImage": "https://images.metmuseum.org/CRDImages/ep/original/DP146453.jpg",
        "artistName": "Jacob van Ruisdael",
        "department": "European Paintings",
        "culture": "",
        "title": "Grainfields",
        "date": 1664,
        "url": "https://www.metmuseum.org/art/collection/search/437547",
        "season": "Summer"
    },
    {
        "objectID": "437517",
        "colorValue": [
            55,
            51,
            25
        ],
        "objectImage": "https://images.metmuseum.org/CRDImages/ep/original/DT240033.jpg",
        "artistName": "Théodore Rousseau",
        "department": "European Paintings",
        "culture": "",
        "title": "A Path among the Rocks",
        "date": 1832,
        "url": "https://www.metmuseum.org/art/collection/search/437517",
        "season": "Summer"
    },
    {
        "objectID": "437436",
        "colorValue": [
            68,
            83,
            66
        ],
        "objectImage": "https://images.metmuseum.org/CRDImages/ep/original/DP265242.jpg",
        "artistName": "Auguste Renoir",
        "department": "European Paintings",
        "culture": "",
        "title": "A Road in Louveciennes",
        "date": 1865,
        "url": "https://www.metmuseum.org/art/collection/search/437436",
        "season": "Summer"
    },
    {
        "objectID": "437549",
        "colorValue": [
            105,
            103,
            92
        ],
        "objectImage": "https://images.metmuseum.org/CRDImages/ep/original/DP145911.jpg",
        "artistName": "Jacob van Ruisdael",
        "department": "European Paintings",
        "culture": "",
        "title": "Wheat Fields",
        "date": 1665,
        "url": "https://www.metmuseum.org/art/collection/search/437549",
        "season": "Summer"
    },
    {
        "objectID": "437586",
        "colorValue": [
            122,
            121,
            111
        ],
        "objectImage": "https://images.metmuseum.org/CRDImages/ep/original/DP143152.jpg",
        "artistName": "Salomon van Ruysdael",
        "department": "European Paintings",
        "culture": "",
        "title": "A Country Road",
        "date": 1648,
        "url": "https://www.metmuseum.org/art/collection/search/437586",
        "season": "Summer"
    },
    {
        "objectID": "437760",
        "colorValue": [
            164,
            157,
            142
        ],
        "objectImage": "https://images.metmuseum.org/CRDImages/ep/original/DP143202.jpg",
        "artistName": "Jacob van Strij",
        "department": "European Paintings",
        "culture": "",
        "title": "Landscape with Cattle",
        "date": 1795,
        "url": "https://www.metmuseum.org/art/collection/search/437760",
        "season": "Summer"
    },
    {
        "objectID": "437683",
        "colorValue": [
            191,
            187,
            188
        ],
        "objectImage": "https://images.metmuseum.org/CRDImages/ep/original/DT1870.jpg",
        "artistName": "Alfred Sisley",
        "department": "European Paintings",
        "culture": "",
        "title": "Sahurs Meadows in Morning Sun",
        "date": 1894,
        "url": "https://www.metmuseum.org/art/collection/search/437683",
        "season": "Summer"
    },
    {
        "objectID": "44876",
        "colorValue": [
            140,
            140,
            140
        ],
        "objectImage": "https://images.metmuseum.org/CRDImages/as/original/14_76_15.jpg",
        "artistName": "Kano Tansui",
        "department": "Asian Art",
        "culture": "Japan",
        "title": "Isle of Immortals with Flanking Chinese Landscapes (Eight Views of Xiao and Xiang)",
        "date": 1800,
        "url": "https://www.metmuseum.org/art/collection/search/44876",
        "season": "Summer"
    },
    {
        "objectID": "438738",
        "colorValue": [
            125,
            117,
            81
        ],
        "objectImage": "https://images.metmuseum.org/CRDImages/ep/original/DP116768.jpg",
        "artistName": "Camille Pissarro",
        "department": "European Paintings",
        "culture": "",
        "title": "Haystacks, Morning, Éragny",
        "date": 1899,
        "url": "https://www.metmuseum.org/art/collection/search/438738",
        "season": "Summer"
    },
    {
        "objectID": "44759",
        "colorValue": [
            194,
            189,
            177
        ],
        "objectImage": "https://images.metmuseum.org/CRDImages/as/original/1985_121_A_sf.jpg",
        "artistName": "Chen Hongshou",
        "department": "Asian Art",
        "culture": "China",
        "title": "Landscapes, Figures, and Flowers",
        "date": 1618,
        "url": "https://www.metmuseum.org/art/collection/search/44759",
        "season": "Summer"
    },
    {
        "objectID": "437980",
        "colorValue": [
            59,
            75,
            52
        ],
        "objectImage": "https://images.metmuseum.org/CRDImages/ep/original/DP130999.jpg",
        "artistName": "Vincent van Gogh",
        "department": "European Paintings",
        "culture": "",
        "title": "Cypresses",
        "date": 1889,
        "url": "https://www.metmuseum.org/art/collection/search/437980",
        "season": "Summer"
    },
    {
        "objectID": "45673",
        "colorValue": [
            116,
            90,
            64
        ],
        "objectImage": "https://images.metmuseum.org/CRDImages/as/original/DP205315_CRD.jpg",
        "artistName": "Unidentified Artist",
        "department": "Asian Art",
        "culture": "China",
        "title": "The Four Seasons",
        "date": 1400,
        "url": "https://www.metmuseum.org/art/collection/search/45673",
        "season": "Summer"
    },
    {
        "objectID": "45201",
        "colorValue": [
            110,
            84,
            55
        ],
        "objectImage": "https://images.metmuseum.org/CRDImages/as/original/DP221036.jpg",
        "artistName": "",
        "department": "Asian Art",
        "culture": "Japan",
        "title": "Descent and Return of Amida to Western Paradise with a Believer's Soul (Gōshō mandara)",
        "date": 1290,
        "url": "https://www.metmuseum.org/art/collection/search/45201",
        "season": "Summer"
    },
    {
        "objectID": "45698",
        "colorValue": [
            194,
            164,
            124
        ],
        "objectImage": "https://images.metmuseum.org/CRDImages/as/original/DP231173.jpg",
        "artistName": "Kano Tan'yū",
        "department": "Asian Art",
        "culture": "Japan",
        "title": "Winter Landscape",
        "date": 1662,
        "url": "https://www.metmuseum.org/art/collection/search/45698",
        "season": "Summer"
    },
    {
        "objectID": "45650",
        "colorValue": [
            204,
            186,
            160
        ],
        "objectImage": "https://images.metmuseum.org/CRDImages/as/original/DP157322_CRD.jpg",
        "artistName": "Zhao Yuan",
        "department": "Asian Art",
        "culture": "China",
        "title": "Landscape",
        "date": 1367,
        "url": "https://www.metmuseum.org/art/collection/search/45650",
        "season": "Summer"
    },
    {
        "objectID": "45700",
        "colorValue": [
            193,
            162,
            122
        ],
        "objectImage": "https://images.metmuseum.org/CRDImages/as/original/DP231177.jpg",
        "artistName": "Kano Tan'yū",
        "department": "Asian Art",
        "culture": "Japan",
        "title": "Summer Landscape",
        "date": 1662,
        "url": "https://www.metmuseum.org/art/collection/search/45700",
        "season": "Summer"
    },
    {
        "objectID": "45738",
        "colorValue": [
            140,
            140,
            140
        ],
        "objectImage": "https://images.metmuseum.org/CRDImages/as/original/14_76_16.jpg",
        "artistName": "Kano Tansui",
        "department": "Asian Art",
        "culture": "Japan",
        "title": "View of Mt. Horai",
        "date": 1800,
        "url": "https://www.metmuseum.org/art/collection/search/45738",
        "season": "Summer"
    },
    {
        "objectID": "49158",
        "colorValue": [
            209,
            202,
            189
        ],
        "objectImage": "https://images.metmuseum.org/CRDImages/as/original/DP153654_CRD.jpg",
        "artistName": "Wu Li",
        "department": "Asian Art",
        "culture": "China",
        "title": "Whiling Away the Summer",
        "date": 1679,
        "url": "https://www.metmuseum.org/art/collection/search/49158",
        "season": "Summer"
    },
    {
        "objectID": "48990",
        "colorValue": [
            169,
            150,
            89
        ],
        "objectImage": "https://images.metmuseum.org/CRDImages/as/original/64_55_1.JPG",
        "artistName": "Ike Taiga",
        "department": "Asian Art",
        "culture": "Japan",
        "title": "Landscapes in Summer and Winter",
        "date": 1723,
        "url": "https://www.metmuseum.org/art/collection/search/48990",
        "season": "Summer"
    },
    {
        "objectID": "48991",
        "colorValue": [
            173,
            150,
            95
        ],
        "objectImage": "https://images.metmuseum.org/CRDImages/as/original/64_55_2.JPG",
        "artistName": "Ike Taiga",
        "department": "Asian Art",
        "culture": "Japan",
        "title": "Landscapes in Summer and Winter",
        "date": 1723,
        "url": "https://www.metmuseum.org/art/collection/search/48991",
        "season": "Summer"
    },
    {
        "objectID": "49017",
        "colorValue": [
            207,
            187,
            164
        ],
        "objectImage": "https://images.metmuseum.org/CRDImages/as/original/DP161053.jpg",
        "artistName": "Yun Xiang",
        "department": "Asian Art",
        "culture": "China",
        "title": "Landscapes after old masters",
        "date": 1638,
        "url": "https://www.metmuseum.org/art/collection/search/49017",
        "season": "Summer"
    },
    {
        "objectID": "49227",
        "colorValue": [
            147,
            120,
            97
        ],
        "objectImage": "https://images.metmuseum.org/CRDImages/as/original/DP274140.jpg",
        "artistName": "Yuan Jiang",
        "department": "Asian Art",
        "culture": "China",
        "title": "The Palace of Nine Perfections",
        "date": 1691,
        "url": "https://www.metmuseum.org/art/collection/search/49227",
        "season": "Summer"
    },
    {
        "objectID": "51850",
        "colorValue": [
            169,
            172,
            165
        ],
        "objectImage": "https://images.metmuseum.org/CRDImages/as/original/62_102.jpg",
        "artistName": "Dong Qichang",
        "department": "Asian Art",
        "culture": "China",
        "title": "Summer Landscape",
        "date": 1555,
        "url": "https://www.metmuseum.org/art/collection/search/51850",
        "season": "Summer"
    },
    {
        "objectID": "53451",
        "colorValue": [
            192,
            173,
            148
        ],
        "objectImage": "https://images.metmuseum.org/CRDImages/as/original/DP-12232-164.jpg",
        "artistName": "Sakaki Hyakusen",
        "department": "Asian Art",
        "culture": "Japan",
        "title": "Snowy Landscape",
        "date": 1620,
        "url": "https://www.metmuseum.org/art/collection/search/53451",
        "season": "Summer"
    },
    {
        "objectID": "57327",
        "colorValue": [
            155,
            128,
            98
        ],
        "objectImage": "https://images.metmuseum.org/CRDImages/as/original/52_160_1_O2.jpg",
        "artistName": "Shibata Zeshin",
        "department": "Asian Art",
        "culture": "Japan",
        "title": "Maple Viewing at Kai'anji Temple",
        "date": 1850,
        "url": "https://www.metmuseum.org/art/collection/search/57327",
        "season": "Summer"
    },
    {
        "objectID": "53463",
        "colorValue": [
            145,
            138,
            126
        ],
        "objectImage": "https://images.metmuseum.org/CRDImages/as/original/DP-12232-233.jpg",
        "artistName": "Yamamoto Baiitsu",
        "department": "Asian Art",
        "culture": "Japan",
        "title": "Landscapes of the Four Seasons",
        "date": 1700,
        "url": "https://www.metmuseum.org/art/collection/search/53463",
        "season": "Summer"
    },
    {
        "objectID": "64872",
        "colorValue": [
            203,
            174,
            135
        ],
        "objectImage": "https://images.metmuseum.org/CRDImages/as/original/DP359324_crd.jpg",
        "artistName": "Genki (Komai Ki)",
        "department": "Asian Art",
        "culture": "Japan",
        "title": "Scenes of the Four Seasons in Kyoto",
        "date": 1778,
        "url": "https://www.metmuseum.org/art/collection/search/64872",
        "season": "Summer"
    },
    {
        "objectID": "65628",
        "colorValue": [
            17,
            18,
            18
        ],
        "objectImage": "https://images.metmuseum.org/CRDImages/as/original/DP-13189-002_crd.jpg",
        "artistName": "Various Artists",
        "department": "Asian Art",
        "culture": "China",
        "title": "Album of Painting and Calligraphy for Maoshu",
        "date": 1666,
        "url": "https://www.metmuseum.org/art/collection/search/65628",
        "season": "Summer"
    },
    {
        "objectID": "670542",
        "colorValue": [
            167,
            125,
            86
        ],
        "objectImage": "https://images.metmuseum.org/CRDImages/as/original/DP-12232-187.jpg",
        "artistName": "Ike Taiga",
        "department": "Asian Art",
        "culture": "Japan",
        "title": "Evening Glow in a Mountain Village and Calligraphy",
        "date": 1767,
        "url": "https://www.metmuseum.org/art/collection/search/670542",
        "season": "Summer"
    }
]